tap_facebook/__init__.py
tap_facebook/client.py
tap_facebook/streams/__init__.py
tap_facebook/streams/ad_accounts.py
tap_facebook/streams/ad_images.py
tap_facebook/streams/ad_insights.py
tap_facebook/streams/ad_labels.py
tap_facebook/streams/ad_videos.py
tap_facebook/streams/ads.py
tap_facebook/streams/adsets.py
tap_facebook/streams/campaign.py
tap_facebook/streams/creative.py
tap_facebook/streams/custom_audiences.py
tap_facebook/streams/custom_conversions.py
tap_facebook/tap.py
meltano_tap_facebook-0.9.0.dist-info/METADATA
meltano_tap_facebook-0.9.0.dist-info/WHEEL
meltano_tap_facebook-0.9.0.dist-info/entry_points.txt
meltano_tap_facebook-0.9.0.dist-info/licenses/LICENSE
meltano_tap_facebook-0.9.0.dist-info/RECORD
