Metadata-Version: 2.4
Name: meltano-tap-facebook
Version: 0.9.0
Summary: `tap-facebook` is a Singer tap for facebook, built with the Meltano SDK for Singer Taps.
License-Expression: Elastic-2.0
License-File: LICENSE
Keywords: ELT,facebook
Author: Meltano
Author-email: hello@meltano.com
Requires-Python: >=3.9
Classifier: Programming Language :: Python :: 3
Classifier: Programming Language :: Python :: 3.9
Classifier: Programming Language :: Python :: 3.10
Classifier: Programming Language :: Python :: 3.11
Classifier: Programming Language :: Python :: 3.12
Classifier: Programming Language :: Python :: 3.13
Classifier: Programming Language :: Python :: 3.14
Requires-Dist: facebook-business (>=21.0.3,<21.1.0)
Requires-Dist: pendulum (>=3.1.0,<3.2.0)
Requires-Dist: requests (>=2.32,<3.0)
Requires-Dist: singer-sdk (>=0.47.0,<0.48.0)
